[
    {
        "id" : 1,
        "title" : "Linh ham",
        "overview" : "Linh la 1 con ham Linh la 1 con ham Linh la 1 con ham Linh la 1 con ham Linh la 1 con hamLinh la 1 con hamLinh la 1 con ham Linh la 1 con ham Linh la 1 con ham "
    },
    {
        "id" : 2,
        "title" : "Linh chap cheng",
        "overview" : "Linh la 1 con ham Linh la 1 con ham Linh la 1 con ham Linh la 1 con ham Linh la 1 con hamLinh la 1 con hamLinh la 1 con ham Linh la 1 con ham Linh la 1 con ham "
    },
    {
        "id" : 3,
        "title" : "Linh ngao",
        "overview" : "Linh la 1 con ham Linh la 1 con ham Linh la 1 con ham Linh la 1 con ham Linh la 1 con hamLinh la 1 con hamLinh la 1 con ham Linh la 1 con ham Linh la 1 con ham "
    },

    {
        "id" : 4,
        "title" : "Linh dien",
        "overview" : "Linh la 1 con ham Linh la 1 con ham Linh la 1 con ham Linh la 1 con ham Linh la 1 con hamLinh la 1 con hamLinh la 1 con ham Linh la 1 con ham Linh la 1 con ham "
    }
]